mkdir_p/__init__.py
mkdir_p/mkdir_p.py
mkdir_p-0.1.1.dist-info/DESCRIPTION.rst
mkdir_p-0.1.1.dist-info/METADATA
mkdir_p-0.1.1.dist-info/RECORD
mkdir_p-0.1.1.dist-info/WHEEL
mkdir_p-0.1.1.dist-info/metadata.json
mkdir_p-0.1.1.dist-info/top_level.txt
