Metadata-Version: 2.0
Name: mkdir-p
Version: 0.1.1
Summary: Python 2 and 3 compatible POSIX mkdir -p.
Home-page: https://github.com/ianlini/mkdir-p
Author: ianlini
Author-email: UNKNOWN
License: UNKNOWN
Platform: UNKNOWN
Classifier: Topic :: Utilities
Classifier: Programming Language :: Python :: 2.7
Classifier: Programming Language :: Python :: 3
